apkfile/__init__.py
apkfile-0.1.7.dist-info/LICENSE
apkfile-0.1.7.dist-info/METADATA
apkfile-0.1.7.dist-info/WHEEL
apkfile-0.1.7.dist-info/top_level.txt
apkfile-0.1.7.dist-info/RECORD
