Metadata-Version: 2.1
Name: apkfile
Version: 0.1.7
Summary: Python wrapper for aapt • ApkFile, XapkFile, ApkmFile
Download-URL: https://pypi.org/project/apkfile/
Author: David Lev
Author-email: davidlev@telegmail.com
License: MIT
Project-URL: Documentation, https://github.com/david-lev/apkfile#readme
Project-URL: Issue Tracker, https://github.com/david-lev/apkfile/issues
Project-URL: Source Code, https://github.com/david-lev/apkfile
Project-URL: Funding, https://github.com/sponsors/david-lev
Keywords: apk,aapt,apkfile,apks,apkm,xapk
Classifier: Development Status :: 5 - Production/Stable
Classifier: Intended Audience :: Developers
Classifier: Topic :: Utilities
Classifier: License :: OSI Approved :: MIT License
Classifier: Operating System :: OS Independent
License-File: LICENSE
